magicimporter/__init__.py
magicimporter/core.py
magicimporter/installer.py
magicimporter/lazy.py
magicimporter-0.1.0.dist-info/licenses/LICENSE
magicimporter-0.1.0.dist-info/METADATA
magicimporter-0.1.0.dist-info/WHEEL
magicimporter-0.1.0.dist-info/top_level.txt
magicimporter-0.1.0.dist-info/RECORD
