Metadata-Version: 2.4
Name: magicimporter
Version: 0.1.0
Summary: Smart Python import wrapper with lazy load and auto-install
Home-page: https://github.com/Deadpool2000/magicimporter
Author: Salil
Author-email: d2kyt@protonmail.com
License: MIT
Project-URL: Documentation, https://github.com/Deadpool2000/magicimporter#readme
Project-URL: Source, https://github.com/Deadpool2000/magicimporter
Project-URL: Issues, https://github.com/Deadpool2000/magicimporter/issues
Keywords: import lazy pip auto-install utility dev-tools
Classifier: Development Status :: 3 - Alpha
Classifier: Intended Audience :: Developers
Classifier: Topic :: Software Development :: Libraries
Classifier: Topic :: Utilities
Classifier: License :: OSI Approved :: MIT License
Classifier: Programming Language :: Python :: 3
Classifier: Programming Language :: Python :: 3.7
Classifier: Programming Language :: Python :: 3.8
Classifier: Programming Language :: Python :: 3.9
Classifier: Programming Language :: Python :: 3.10
Classifier: Operating System :: OS Independent
Requires-Python: >=3.7
License-File: LICENSE
Dynamic: author
Dynamic: author-email
Dynamic: classifier
Dynamic: description
Dynamic: description-content-type
Dynamic: home-page
Dynamic: keywords
Dynamic: license
Dynamic: license-file
Dynamic: project-url
Dynamic: requires-python
Dynamic: summary
